{"startedAt":1665371623360,"id":"wFCIAZxa61ICRdaGcMirSQ","suite":"주문내역 상세페이지","title":"정상적인 주문 ","file":"/Users/seonghwan/Desktop/makaoGift-frontend/tests/OrderDetail_test.js","steps":[{"type":"meta","result":"passed","actor":"I","name":"setupProducts","args":[],"opens":"I-setupProducts0_UxCKeS-fU4MUn8oSbWQg5"},{"id":"9njCtAbbicq-GHc-RSRxv","testId":"wFCIAZxa61ICRdaGcMirSQ","at":261,"duration":258,"actor":"I","humanized":"am on page","humanizedArgs":"\"http://localhost:8000/backdoor/setup-product\"","status":"success","name":"amOnPage","args":["http://localhost:8000/backdoor/setup-product"],"store":{"debugMode":false,"timeouts":true,"actor":{}},"logs":[],"section":"I-setupProducts0_UxCKeS-fU4MUn8oSbWQg5","metaStep":{"actor":"I","name":"setupProducts","args":[]},"stack":{"stackFrameOfStep":"    at Step.setTrace (/Users/seonghwan/Desktop/makaoGift-frontend/node_modules/codeceptjs/lib/step.js:102:11)"},"startedAt":1665371623363,"snapshot":{"hasScreenshot":true,"hasSnapshot":true,"id":"9njCtAbbicq-GHc-RSRxv","pageUrl":"http://localhost:8000/backdoor/setup-product","pageTitle":"","sourceContentType":"html","height":720,"width":1280}},{"type":"meta","result":"passed","actor":"I","name":"setupDatabase","args":[],"opens":"I-setupDatabase0_F15AyngYDBsfogKdnoL7m"},{"id":"aNkH95rdGt_MANjyu_qek","testId":"wFCIAZxa61ICRdaGcMirSQ","at":571,"duration":306,"actor":"I","humanized":"am on page","humanizedArgs":"\"http://localhost:8000/backdoor/setup-database\"","status":"success","name":"amOnPage","args":["http://localhost:8000/backdoor/setup-database"],"store":{"debugMode":false,"timeouts":true,"actor":{}},"logs":[],"section":"I-setupDatabase0_F15AyngYDBsfogKdnoL7m","metaStep":{"actor":"I","name":"setupDatabase","args":[]},"stack":{"stackFrameInTest":"    at Test.<anonymous> (/Users/seonghwan/Desktop/makaoGift-frontend/tests/OrderDetail_test.js:8:5)","stackFrameOfStep":"    at Step.setTrace (/Users/seonghwan/Desktop/makaoGift-frontend/node_modules/codeceptjs/lib/step.js:102:11)"},"startedAt":1665371623625,"snapshot":{"hasScreenshot":true,"hasSnapshot":true,"id":"aNkH95rdGt_MANjyu_qek","pageUrl":"http://localhost:8000/backdoor/setup-database","pageTitle":"","sourceContentType":"html","height":720,"width":1280}},{"type":"meta","result":"passed","actor":"I","name":"login","args":["tidls45"],"opens":"I-login0_p-Vb_JfDtp3Sig49uiwEE"},{"id":"3qFaeTHKz6CPZLieK6Fk_","testId":"wFCIAZxa61ICRdaGcMirSQ","at":2057,"duration":1485,"actor":"I","humanized":"am on page","humanizedArgs":"\"/\"","status":"success","name":"amOnPage","args":["/"],"store":{"debugMode":false,"timeouts":true,"actor":{}},"logs":[],"section":"I-login0_p-Vb_JfDtp3Sig49uiwEE","metaStep":{"actor":"I","name":"login","args":["tidls45"]},"stack":{"stackFrameInTest":"    at Test.<anonymous> (/Users/seonghwan/Desktop/makaoGift-frontend/tests/OrderDetail_test.js:10:5)","stackFrameOfStep":"    at Step.setTrace (/Users/seonghwan/Desktop/makaoGift-frontend/node_modules/codeceptjs/lib/step.js:102:11)"},"startedAt":1665371623932,"snapshot":{"hasScreenshot":true,"hasSnapshot":true,"id":"3qFaeTHKz6CPZLieK6Fk_","pageUrl":"http://localhost:8080/","pageTitle":"React Demo","sourceContentType":"html","height":720,"width":1280}},{"id":"fh0VCjOnqmzQ-MDd-a6jY","testId":"wFCIAZxa61ICRdaGcMirSQ","at":2343,"duration":284,"actor":"I","humanized":"click","humanizedArgs":"\"로그인\"","status":"success","name":"click","args":["로그인"],"store":{"debugMode":false,"timeouts":true,"actor":{}},"logs":[],"section":"I-login0_p-Vb_JfDtp3Sig49uiwEE","metaStep":{"actor":"I","name":"login","args":["tidls45"]},"stack":{"stackFrameInTest":"    at Test.<anonymous> (/Users/seonghwan/Desktop/makaoGift-frontend/tests/OrderDetail_test.js:10:5)","stackFrameOfStep":"    at Step.setTrace (/Users/seonghwan/Desktop/makaoGift-frontend/node_modules/codeceptjs/lib/step.js:102:11)"},"startedAt":1665371625419,"snapshot":{"hasScreenshot":true,"hasSnapshot":true,"id":"fh0VCjOnqmzQ-MDd-a6jY","pageUrl":"http://localhost:8080/login","pageTitle":"React Demo","sourceContentType":"html","height":720,"width":1280}},{"id":"6ouKMMNH3Gm6cPZ9QkeRk","testId":"wFCIAZxa61ICRdaGcMirSQ","at":2671,"duration":328,"actor":"I","humanized":"fill field","humanizedArgs":"\"아이디\", \"tidls45\"","status":"success","name":"fillField","args":["아이디","tidls45"],"store":{"debugMode":false,"timeouts":true,"actor":{}},"logs":[],"section":"I-login0_p-Vb_JfDtp3Sig49uiwEE","metaStep":{"actor":"I","name":"login","args":["tidls45"]},"stack":{"stackFrameInTest":"    at Test.<anonymous> (/Users/seonghwan/Desktop/makaoGift-frontend/tests/OrderDetail_test.js:10:5)","stackFrameOfStep":"    at Step.setTrace (/Users/seonghwan/Desktop/makaoGift-frontend/node_modules/codeceptjs/lib/step.js:102:11)"},"startedAt":1665371625703,"snapshot":{"hasScreenshot":true,"hasSnapshot":true,"id":"6ouKMMNH3Gm6cPZ9QkeRk","pageUrl":"http://localhost:8080/login","pageTitle":"React Demo","sourceContentType":"html","height":720,"width":1280}},{"id":"htSqNLtz-lVVH2I6dyHkh","testId":"wFCIAZxa61ICRdaGcMirSQ","at":3047,"duration":376,"actor":"I","humanized":"fill field","humanizedArgs":"\"비밀번호\", \"Tjdghks245@\"","status":"success","name":"fillField","args":["비밀번호","Tjdghks245@"],"store":{"debugMode":false,"timeouts":true,"actor":{}},"logs":[],"section":"I-login0_p-Vb_JfDtp3Sig49uiwEE","metaStep":{"actor":"I","name":"login","args":["tidls45"]},"stack":{"stackFrameInTest":"    at Test.<anonymous> (/Users/seonghwan/Desktop/makaoGift-frontend/tests/OrderDetail_test.js:10:5)","stackFrameOfStep":"    at Step.setTrace (/Users/seonghwan/Desktop/makaoGift-frontend/node_modules/codeceptjs/lib/step.js:102:11)"},"startedAt":1665371626031,"snapshot":{"hasScreenshot":true,"hasSnapshot":true,"id":"htSqNLtz-lVVH2I6dyHkh","pageUrl":"http://localhost:8080/login","pageTitle":"React Demo","sourceContentType":"html","height":720,"width":1280}},{"id":"FTZ9tgmdbZR9Mha1roZas","testId":"wFCIAZxa61ICRdaGcMirSQ","at":3313,"duration":265,"actor":"I","humanized":"click","humanizedArgs":"\"로그인하기\"","status":"success","name":"click","args":["로그인하기"],"store":{"debugMode":false,"timeouts":true,"actor":{}},"logs":[],"section":"I-login0_p-Vb_JfDtp3Sig49uiwEE","metaStep":{"actor":"I","name":"login","args":["tidls45"]},"stack":{"stackFrameInTest":"    at Test.<anonymous> (/Users/seonghwan/Desktop/makaoGift-frontend/tests/OrderDetail_test.js:10:5)","stackFrameOfStep":"    at Step.setTrace (/Users/seonghwan/Desktop/makaoGift-frontend/node_modules/codeceptjs/lib/step.js:102:11)"},"startedAt":1665371626408,"snapshot":{"hasScreenshot":true,"hasSnapshot":true,"id":"FTZ9tgmdbZR9Mha1roZas","pageUrl":"http://localhost:8080/","pageTitle":"React Demo","sourceContentType":"html","height":720,"width":1280}},{"id":"J0YCmp_TA3-E1LkaFqu9G","testId":"wFCIAZxa61ICRdaGcMirSQ","at":3434,"duration":120,"actor":"I","humanized":"wait for text","humanizedArgs":"\"로그아웃\"","status":"success","name":"waitForText","args":["로그아웃"],"store":{"debugMode":false,"timeouts":true,"actor":{}},"logs":[],"section":"I-login0_p-Vb_JfDtp3Sig49uiwEE","metaStep":{"actor":"I","name":"login","args":["tidls45"]},"stack":{"stackFrameInTest":"    at Test.<anonymous> (/Users/seonghwan/Desktop/makaoGift-frontend/tests/OrderDetail_test.js:10:5)","stackFrameOfStep":"    at Step.setTrace (/Users/seonghwan/Desktop/makaoGift-frontend/node_modules/codeceptjs/lib/step.js:102:11)"},"startedAt":1665371626674,"snapshot":{"hasScreenshot":true,"hasSnapshot":true,"id":"J0YCmp_TA3-E1LkaFqu9G","pageUrl":"http://localhost:8080/","pageTitle":"React Demo","sourceContentType":"html","height":720,"width":1280}},{"id":"WYOTTLuoRFX8Cq8K70LTK","testId":"wFCIAZxa61ICRdaGcMirSQ","at":3775,"duration":341,"actor":"I","humanized":"am on page","humanizedArgs":"\"/\"","status":"success","name":"amOnPage","args":["/"],"store":{"debugMode":false,"timeouts":true,"actor":{}},"logs":[],"stack":{"stackFrameInTest":"    at Test.<anonymous> (/Users/seonghwan/Desktop/makaoGift-frontend/tests/OrderDetail_test.js:11:5)","stackFrameOfStep":"    at Step.setTrace (/Users/seonghwan/Desktop/makaoGift-frontend/node_modules/codeceptjs/lib/step.js:102:11)"},"startedAt":1665371626794,"snapshot":{"hasScreenshot":true,"hasSnapshot":true,"id":"WYOTTLuoRFX8Cq8K70LTK","pageUrl":"http://localhost:8080/","pageTitle":"React Demo","sourceContentType":"html","height":720,"width":1280}},{"id":"cthsVl1oS0LQazOhMf8Iw","testId":"wFCIAZxa61ICRdaGcMirSQ","at":4085,"duration":309,"actor":"I","humanized":"click","humanizedArgs":"\"스토어\"","status":"success","name":"click","args":["스토어"],"store":{"debugMode":false,"timeouts":true,"actor":{}},"logs":[],"stack":{"stackFrameInTest":"    at Test.<anonymous> (/Users/seonghwan/Desktop/makaoGift-frontend/tests/OrderDetail_test.js:13:5)","stackFrameOfStep":"    at Step.setTrace (/Users/seonghwan/Desktop/makaoGift-frontend/node_modules/codeceptjs/lib/step.js:102:11)"},"startedAt":1665371627136,"snapshot":{"hasScreenshot":true,"hasSnapshot":true,"id":"cthsVl1oS0LQazOhMf8Iw","pageUrl":"http://localhost:8080/products","pageTitle":"React Demo","sourceContentType":"html","height":720,"width":1280}},{"id":"tPso89L3w_SI3wmWFfwos","testId":"wFCIAZxa61ICRdaGcMirSQ","at":4360,"duration":274,"actor":"I","humanized":"click","humanizedArgs":"\"갤럭시S22\"","status":"success","name":"click","args":["갤럭시S22"],"store":{"debugMode":false,"timeouts":true,"actor":{}},"logs":[],"stack":{"stackFrameInTest":"    at Test.<anonymous> (/Users/seonghwan/Desktop/makaoGift-frontend/tests/OrderDetail_test.js:15:5)","stackFrameOfStep":"    at Step.setTrace (/Users/seonghwan/Desktop/makaoGift-frontend/node_modules/codeceptjs/lib/step.js:102:11)"},"startedAt":1665371627446,"snapshot":{"hasScreenshot":true,"hasSnapshot":true,"id":"tPso89L3w_SI3wmWFfwos","pageUrl":"http://localhost:8080/products/2","pageTitle":"React Demo","sourceContentType":"html","height":720,"width":1280}},{"id":"u4BVJLrntjzlcplOc2l9q","testId":"wFCIAZxa61ICRdaGcMirSQ","at":4481,"duration":120,"actor":"I","humanized":"see","humanizedArgs":"\"총 상품금액:100,000원\"","status":"success","name":"see","args":["총 상품금액:100,000원"],"store":{"debugMode":false,"timeouts":true,"actor":{}},"logs":[],"stack":{"stackFrameInTest":"    at Test.<anonymous> (/Users/seonghwan/Desktop/makaoGift-frontend/tests/OrderDetail_test.js:17:5)","stackFrameOfStep":"    at Step.setTrace (/Users/seonghwan/Desktop/makaoGift-frontend/node_modules/codeceptjs/lib/step.js:102:11)"},"startedAt":1665371627721,"snapshot":{"hasScreenshot":true,"hasSnapshot":true,"id":"u4BVJLrntjzlcplOc2l9q","pageUrl":"http://localhost:8080/products/2","pageTitle":"React Demo","sourceContentType":"html","height":720,"width":1280}},{"id":"tJT53ZCOktklx_6NuQy8T","testId":"wFCIAZxa61ICRdaGcMirSQ","at":4771,"duration":289,"actor":"I","humanized":"click","humanizedArgs":"\"button[name=\"present-button\"]\"","status":"success","name":"click","args":["button[name=\"present-button\"]"],"store":{"debugMode":false,"timeouts":true,"actor":{}},"logs":[],"stack":{"stackFrameInTest":"    at Test.<anonymous> (/Users/seonghwan/Desktop/makaoGift-frontend/tests/OrderDetail_test.js:19:5)","stackFrameOfStep":"    at Step.setTrace (/Users/seonghwan/Desktop/makaoGift-frontend/node_modules/codeceptjs/lib/step.js:102:11)"},"startedAt":1665371627842,"snapshot":{"hasScreenshot":true,"hasSnapshot":true,"id":"tJT53ZCOktklx_6NuQy8T","pageUrl":"http://localhost:8080/order","pageTitle":"React Demo","sourceContentType":"html","height":720,"width":1280}},{"id":"B7-JNdz5rpxhCBgoOVdTJ","testId":"wFCIAZxa61ICRdaGcMirSQ","at":4901,"duration":130,"actor":"I","humanized":"see","humanizedArgs":"\"받는 분 성함\"","status":"success","name":"see","args":["받는 분 성함"],"store":{"debugMode":false,"timeouts":true,"actor":{}},"logs":[],"stack":{"stackFrameInTest":"    at Test.<anonymous> (/Users/seonghwan/Desktop/makaoGift-frontend/tests/OrderDetail_test.js:21:5)","stackFrameOfStep":"    at Step.setTrace (/Users/seonghwan/Desktop/makaoGift-frontend/node_modules/codeceptjs/lib/step.js:102:11)"},"startedAt":1665371628131,"snapshot":{"hasScreenshot":true,"hasSnapshot":true,"id":"B7-JNdz5rpxhCBgoOVdTJ","pageUrl":"http://localhost:8080/order","pageTitle":"React Demo","sourceContentType":"html","height":720,"width":1280}},{"id":"D74V79kDenED5aEGGiiPg","testId":"wFCIAZxa61ICRdaGcMirSQ","at":5010,"duration":108,"actor":"I","humanized":"see","humanizedArgs":"\"받는 분 주소\"","status":"success","name":"see","args":["받는 분 주소"],"store":{"debugMode":false,"timeouts":true,"actor":{}},"logs":[],"stack":{"stackFrameInTest":"    at Test.<anonymous> (/Users/seonghwan/Desktop/makaoGift-frontend/tests/OrderDetail_test.js:22:5)","stackFrameOfStep":"    at Step.setTrace (/Users/seonghwan/Desktop/makaoGift-frontend/node_modules/codeceptjs/lib/step.js:102:11)"},"startedAt":1665371628262,"snapshot":{"hasScreenshot":true,"hasSnapshot":true,"id":"D74V79kDenED5aEGGiiPg","pageUrl":"http://localhost:8080/order","pageTitle":"React Demo","sourceContentType":"html","height":720,"width":1280}},{"id":"FR18a_ow19Ytu6nUParhE","testId":"wFCIAZxa61ICRdaGcMirSQ","at":5132,"duration":121,"actor":"I","humanized":"see","humanizedArgs":"\"받는 분께 보내는 메시지\"","status":"success","name":"see","args":["받는 분께 보내는 메시지"],"store":{"debugMode":false,"timeouts":true,"actor":{}},"logs":[],"stack":{"stackFrameInTest":"    at Test.<anonymous> (/Users/seonghwan/Desktop/makaoGift-frontend/tests/OrderDetail_test.js:23:5)","stackFrameOfStep":"    at Step.setTrace (/Users/seonghwan/Desktop/makaoGift-frontend/node_modules/codeceptjs/lib/step.js:102:11)"},"startedAt":1665371628371,"snapshot":{"hasScreenshot":true,"hasSnapshot":true,"id":"FR18a_ow19Ytu6nUParhE","pageUrl":"http://localhost:8080/order","pageTitle":"React Demo","sourceContentType":"html","height":720,"width":1280}},{"id":"WWfhiMrmw9K9i639pAjVn","testId":"wFCIAZxa61ICRdaGcMirSQ","at":5394,"duration":262,"actor":"I","humanized":"fill field","humanizedArgs":"\"받는 분 성함\", \"테스트\"","status":"success","name":"fillField","args":["받는 분 성함","테스트"],"store":{"debugMode":false,"timeouts":true,"actor":{}},"logs":[],"stack":{"stackFrameInTest":"    at Test.<anonymous> (/Users/seonghwan/Desktop/makaoGift-frontend/tests/OrderDetail_test.js:25:5)","stackFrameOfStep":"    at Step.setTrace (/Users/seonghwan/Desktop/makaoGift-frontend/node_modules/codeceptjs/lib/step.js:102:11)"},"startedAt":1665371628492,"snapshot":{"hasScreenshot":true,"hasSnapshot":true,"id":"WWfhiMrmw9K9i639pAjVn","pageUrl":"http://localhost:8080/order","pageTitle":"React Demo","sourceContentType":"html","height":720,"width":1280}},{"id":"EcLC1HiE_P6UlEkLr37Hz","testId":"wFCIAZxa61ICRdaGcMirSQ","at":5686,"duration":291,"actor":"I","humanized":"fill field","humanizedArgs":"\"받는 분 주소\", \"울산광역시\"","status":"success","name":"fillField","args":["받는 분 주소","울산광역시"],"store":{"debugMode":false,"timeouts":true,"actor":{}},"logs":[],"stack":{"stackFrameInTest":"    at Test.<anonymous> (/Users/seonghwan/Desktop/makaoGift-frontend/tests/OrderDetail_test.js:26:5)","stackFrameOfStep":"    at Step.setTrace (/Users/seonghwan/Desktop/makaoGift-frontend/node_modules/codeceptjs/lib/step.js:102:11)"},"startedAt":1665371628755,"snapshot":{"hasScreenshot":true,"hasSnapshot":true,"id":"EcLC1HiE_P6UlEkLr37Hz","pageUrl":"http://localhost:8080/order","pageTitle":"React Demo","sourceContentType":"html","height":720,"width":1280}},{"id":"bQUMa17LUlvPCI_ne43T1","testId":"wFCIAZxa61ICRdaGcMirSQ","at":5946,"duration":259,"actor":"I","humanized":"fill field","humanizedArgs":"\"받는 분께 보내는 메시지\", \"테스트\"","status":"success","name":"fillField","args":["받는 분께 보내는 메시지","테스트"],"store":{"debugMode":false,"timeouts":true,"actor":{}},"logs":[],"stack":{"stackFrameInTest":"    at Test.<anonymous> (/Users/seonghwan/Desktop/makaoGift-frontend/tests/OrderDetail_test.js:27:5)","stackFrameOfStep":"    at Step.setTrace (/Users/seonghwan/Desktop/makaoGift-frontend/node_modules/codeceptjs/lib/step.js:102:11)"},"startedAt":1665371629047,"snapshot":{"hasScreenshot":true,"hasSnapshot":true,"id":"bQUMa17LUlvPCI_ne43T1","pageUrl":"http://localhost:8080/order","pageTitle":"React Demo","sourceContentType":"html","height":720,"width":1280}},{"id":"QTjVIHADvfetXFg3Jt2eg","testId":"wFCIAZxa61ICRdaGcMirSQ","at":6224,"duration":277,"actor":"I","humanized":"click","humanizedArgs":"\"button[name=\"order-button\"]\"","status":"success","name":"click","args":["button[name=\"order-button\"]"],"store":{"debugMode":false,"timeouts":true,"actor":{}},"logs":[],"stack":{"stackFrameInTest":"    at Test.<anonymous> (/Users/seonghwan/Desktop/makaoGift-frontend/tests/OrderDetail_test.js:29:5)","stackFrameOfStep":"    at Step.setTrace (/Users/seonghwan/Desktop/makaoGift-frontend/node_modules/codeceptjs/lib/step.js:102:11)"},"startedAt":1665371629307,"snapshot":{"hasScreenshot":true,"hasSnapshot":true,"id":"QTjVIHADvfetXFg3Jt2eg","pageUrl":"http://localhost:8080/orders","pageTitle":"React Demo","sourceContentType":"html","height":720,"width":1280}},{"id":"cghXdDUQ4q3lKURUwn--4","testId":"wFCIAZxa61ICRdaGcMirSQ","at":6359,"duration":135,"actor":"I","humanized":"see","humanizedArgs":"\"내가 주문한 내역입니다\"","status":"success","name":"see","args":["내가 주문한 내역입니다"],"store":{"debugMode":false,"timeouts":true,"actor":{}},"logs":[],"stack":{"stackFrameInTest":"    at Test.<anonymous> (/Users/seonghwan/Desktop/makaoGift-frontend/tests/OrderDetail_test.js:31:5)","stackFrameOfStep":"    at Step.setTrace (/Users/seonghwan/Desktop/makaoGift-frontend/node_modules/codeceptjs/lib/step.js:102:11)"},"startedAt":1665371629584,"snapshot":{"hasScreenshot":true,"hasSnapshot":true,"id":"cghXdDUQ4q3lKURUwn--4","pageUrl":"http://localhost:8080/orders","pageTitle":"React Demo","sourceContentType":"html","height":720,"width":1280}},{"id":"pb07z6PcPTpgFPgCRRwj9","testId":"wFCIAZxa61ICRdaGcMirSQ","at":6487,"duration":127,"actor":"I","humanized":"see","humanizedArgs":"\"내 잔액: 900,000원\"","status":"success","name":"see","args":["내 잔액: 900,000원"],"store":{"debugMode":false,"timeouts":true,"actor":{}},"logs":[],"stack":{"stackFrameInTest":"    at Test.<anonymous> (/Users/seonghwan/Desktop/makaoGift-frontend/tests/OrderDetail_test.js:32:5)","stackFrameOfStep":"    at Step.setTrace (/Users/seonghwan/Desktop/makaoGift-frontend/node_modules/codeceptjs/lib/step.js:102:11)"},"startedAt":1665371629720,"snapshot":{"hasScreenshot":true,"hasSnapshot":true,"id":"pb07z6PcPTpgFPgCRRwj9","pageUrl":"http://localhost:8080/orders","pageTitle":"React Demo","sourceContentType":"html","height":720,"width":1280}},{"id":"4XL70FVlzRQUAT1IuzB-O","testId":"wFCIAZxa61ICRdaGcMirSQ","at":6780,"duration":292,"actor":"I","humanized":"am on page","humanizedArgs":"\"/\"","status":"success","name":"amOnPage","args":["/"],"store":{"debugMode":false,"timeouts":true,"actor":{}},"logs":[],"stack":{"stackFrameInTest":"    at Test.<anonymous> (/Users/seonghwan/Desktop/makaoGift-frontend/tests/OrderDetail_test.js:34:5)","stackFrameOfStep":"    at Step.setTrace (/Users/seonghwan/Desktop/makaoGift-frontend/node_modules/codeceptjs/lib/step.js:102:11)"},"startedAt":1665371629848,"snapshot":{"hasScreenshot":true,"hasSnapshot":true,"id":"4XL70FVlzRQUAT1IuzB-O","pageUrl":"http://localhost:8080/","pageTitle":"React Demo","sourceContentType":"html","height":720,"width":1280}},{"id":"4s7uJx_Dj2JBu4DO9xuNH","testId":"wFCIAZxa61ICRdaGcMirSQ","at":7055,"duration":274,"actor":"I","humanized":"click","humanizedArgs":"\"주문조회\"","status":"success","name":"click","args":["주문조회"],"store":{"debugMode":false,"timeouts":true,"actor":{}},"logs":[],"stack":{"stackFrameInTest":"    at Test.<anonymous> (/Users/seonghwan/Desktop/makaoGift-frontend/tests/OrderDetail_test.js:36:5)","stackFrameOfStep":"    at Step.setTrace (/Users/seonghwan/Desktop/makaoGift-frontend/node_modules/codeceptjs/lib/step.js:102:11)"},"startedAt":1665371630141,"snapshot":{"hasScreenshot":true,"hasSnapshot":true,"id":"4s7uJx_Dj2JBu4DO9xuNH","pageUrl":"http://localhost:8080/orders","pageTitle":"React Demo","sourceContentType":"html","height":720,"width":1280}},{"id":"Asa0WKBfNkgIqAkG0E6nO","testId":"wFCIAZxa61ICRdaGcMirSQ","at":83627,"duration":76572,"actor":"I","humanized":"click","humanizedArgs":"\"갤럭시S22\"","status":"success","name":"click","args":["갤럭시S22"],"store":{"debugMode":false,"timeouts":true,"actor":{}},"logs":[],"stack":{"stackFrameInTest":"    at Test.<anonymous> (/Users/seonghwan/Desktop/makaoGift-frontend/tests/OrderDetail_test.js:38:5)","stackFrameOfStep":"    at Step.setTrace (/Users/seonghwan/Desktop/makaoGift-frontend/node_modules/codeceptjs/lib/step.js:102:11)"},"startedAt":1665371630415,"snapshot":{"hasScreenshot":true,"hasSnapshot":true,"id":"Asa0WKBfNkgIqAkG0E6nO","pageUrl":"http://localhost:8080/orders/64","pageTitle":"React Demo","sourceContentType":"html","height":720,"width":1280}},{"id":"F77NkhAtuJtGSl9F4jPzR","testId":"wFCIAZxa61ICRdaGcMirSQ","at":83749,"duration":121,"actor":"I","humanized":"see","humanizedArgs":"\"삼성전자\"","status":"success","name":"see","args":["삼성전자"],"store":{"debugMode":false,"timeouts":true,"actor":{}},"logs":[],"stack":{"stackFrameInTest":"    at Test.<anonymous> (/Users/seonghwan/Desktop/makaoGift-frontend/tests/OrderDetail_test.js:40:5)","stackFrameOfStep":"    at Step.setTrace (/Users/seonghwan/Desktop/makaoGift-frontend/node_modules/codeceptjs/lib/step.js:102:11)"},"startedAt":1665371706988,"snapshot":{"hasScreenshot":true,"hasSnapshot":true,"id":"F77NkhAtuJtGSl9F4jPzR","pageUrl":"http://localhost:8080/orders/64","pageTitle":"React Demo","sourceContentType":"html","height":720,"width":1280}},{"id":"NQZv-07JIceZ9QFV1F2Rf","testId":"wFCIAZxa61ICRdaGcMirSQ","at":83870,"duration":120,"actor":"I","humanized":"see","humanizedArgs":"\"갤럭시S22\"","status":"success","name":"see","args":["갤럭시S22"],"store":{"debugMode":false,"timeouts":true,"actor":{}},"logs":[],"stack":{"stackFrameInTest":"    at Test.<anonymous> (/Users/seonghwan/Desktop/makaoGift-frontend/tests/OrderDetail_test.js:41:5)","stackFrameOfStep":"    at Step.setTrace (/Users/seonghwan/Desktop/makaoGift-frontend/node_modules/codeceptjs/lib/step.js:102:11)"},"startedAt":1665371707110,"snapshot":{"hasScreenshot":true,"hasSnapshot":true,"id":"NQZv-07JIceZ9QFV1F2Rf","pageUrl":"http://localhost:8080/orders/64","pageTitle":"React Demo","sourceContentType":"html","height":720,"width":1280}},{"id":"4tVwRlo1hBtkLfiaN_uZT","testId":"wFCIAZxa61ICRdaGcMirSQ","at":83982,"duration":111,"actor":"I","humanized":"see","humanizedArgs":"\"구매수량 : 1\"","status":"success","name":"see","args":["구매수량 : 1"],"store":{"debugMode":false,"timeouts":true,"actor":{}},"logs":[],"stack":{"stackFrameInTest":"    at Test.<anonymous> (/Users/seonghwan/Desktop/makaoGift-frontend/tests/OrderDetail_test.js:42:5)","stackFrameOfStep":"    at Step.setTrace (/Users/seonghwan/Desktop/makaoGift-frontend/node_modules/codeceptjs/lib/step.js:102:11)"},"startedAt":1665371707231,"snapshot":{"hasScreenshot":true,"hasSnapshot":true,"id":"4tVwRlo1hBtkLfiaN_uZT","pageUrl":"http://localhost:8080/orders/64","pageTitle":"React Demo","sourceContentType":"html","height":720,"width":1280}},{"id":"JhTVfZx4hIZIcgUHngBtD","testId":"wFCIAZxa61ICRdaGcMirSQ","at":84102,"duration":119,"actor":"I","humanized":"see","humanizedArgs":"\"총 상품금액 : 100,000원\"","status":"success","name":"see","args":["총 상품금액 : 100,000원"],"store":{"debugMode":false,"timeouts":true,"actor":{}},"logs":[],"stack":{"stackFrameInTest":"    at Test.<anonymous> (/Users/seonghwan/Desktop/makaoGift-frontend/tests/OrderDetail_test.js:43:5)","stackFrameOfStep":"    at Step.setTrace (/Users/seonghwan/Desktop/makaoGift-frontend/node_modules/codeceptjs/lib/step.js:102:11)"},"startedAt":1665371707343,"snapshot":{"hasScreenshot":true,"hasSnapshot":true,"id":"JhTVfZx4hIZIcgUHngBtD","pageUrl":"http://localhost:8080/orders/64","pageTitle":"React Demo","sourceContentType":"html","height":720,"width":1280}},{"id":"QHRsUM5tcPcQyeVtDH2c_","testId":"wFCIAZxa61ICRdaGcMirSQ","at":84213,"duration":110,"actor":"I","humanized":"see","humanizedArgs":"\"구매일 : 2022/10/10\"","status":"success","name":"see","args":["구매일 : 2022/10/10"],"store":{"debugMode":false,"timeouts":true,"actor":{}},"logs":[],"stack":{"stackFrameInTest":"    at Test.<anonymous> (/Users/seonghwan/Desktop/makaoGift-frontend/tests/OrderDetail_test.js:44:5)","stackFrameOfStep":"    at Step.setTrace (/Users/seonghwan/Desktop/makaoGift-frontend/node_modules/codeceptjs/lib/step.js:102:11)"},"startedAt":1665371707463,"snapshot":{"hasScreenshot":true,"hasSnapshot":true,"id":"QHRsUM5tcPcQyeVtDH2c_","pageUrl":"http://localhost:8080/orders/64","pageTitle":"React Demo","sourceContentType":"html","height":720,"width":1280}},{"id":"_F9_xb52VS7jTLrnux1fZ","testId":"wFCIAZxa61ICRdaGcMirSQ","at":84332,"duration":118,"actor":"I","humanized":"see","humanizedArgs":"\"받는 분 : 테스트\"","status":"success","name":"see","args":["받는 분 : 테스트"],"store":{"debugMode":false,"timeouts":true,"actor":{}},"logs":[],"stack":{"stackFrameInTest":"    at Test.<anonymous> (/Users/seonghwan/Desktop/makaoGift-frontend/tests/OrderDetail_test.js:45:5)","stackFrameOfStep":"    at Step.setTrace (/Users/seonghwan/Desktop/makaoGift-frontend/node_modules/codeceptjs/lib/step.js:102:11)"},"startedAt":1665371707574,"snapshot":{"hasScreenshot":true,"hasSnapshot":true,"id":"_F9_xb52VS7jTLrnux1fZ","pageUrl":"http://localhost:8080/orders/64","pageTitle":"React Demo","sourceContentType":"html","height":720,"width":1280}},{"id":"Evff-WT6xMTY2BJh1Z0S9","testId":"wFCIAZxa61ICRdaGcMirSQ","at":84452,"duration":119,"actor":"I","humanized":"see","humanizedArgs":"\"받는 분 주소 : 울산광역시\"","status":"success","name":"see","args":["받는 분 주소 : 울산광역시"],"store":{"debugMode":false,"timeouts":true,"actor":{}},"logs":[],"stack":{"stackFrameInTest":"    at Test.<anonymous> (/Users/seonghwan/Desktop/makaoGift-frontend/tests/OrderDetail_test.js:46:5)","stackFrameOfStep":"    at Step.setTrace (/Users/seonghwan/Desktop/makaoGift-frontend/node_modules/codeceptjs/lib/step.js:102:11)"},"startedAt":1665371707693,"snapshot":{"hasScreenshot":true,"hasSnapshot":true,"id":"Evff-WT6xMTY2BJh1Z0S9","pageUrl":"http://localhost:8080/orders/64","pageTitle":"React Demo","sourceContentType":"html","height":720,"width":1280}},{"id":"sojlTfeprRImNIrnVOWbE","testId":"wFCIAZxa61ICRdaGcMirSQ","at":84562,"duration":110,"actor":"I","humanized":"see","humanizedArgs":"\"받는 분께 보내는 메시지 : 테스트\"","status":"success","name":"see","args":["받는 분께 보내는 메시지 : 테스트"],"store":{"debugMode":false,"timeouts":true,"actor":{}},"logs":[],"stack":{"stackFrameInTest":"    at Test.<anonymous> (/Users/seonghwan/Desktop/makaoGift-frontend/tests/OrderDetail_test.js:47:5)","stackFrameOfStep":"    at Step.setTrace (/Users/seonghwan/Desktop/makaoGift-frontend/node_modules/codeceptjs/lib/step.js:102:11)"},"startedAt":1665371707812,"snapshot":{"hasScreenshot":true,"hasSnapshot":true,"id":"sojlTfeprRImNIrnVOWbE","pageUrl":"http://localhost:8080/orders/64","pageTitle":"React Demo","sourceContentType":"html","height":720,"width":1280}}],"result":"passed","duration":84.564}